{
  "pensamentos": [
    {
      "id": 1,
      "conteudo": "We are the champions my friend !!",
      "autoria": "Queen",
      "modelo": "modelo1"
    },
    {
      "id": 2,
      "conteudo": "Continue a codar... Continue a codar...",
      "autoria": "Aline",
      "modelo": "modelo2"
    },
    {
      "conteudo": "“Que a Força esteja com você!”",
      "autoria": "Star Wars",
      "modelo": "modelo3",
      "id": 7
    },
    {
      "conteudo": "Você é capaz",
      "autoria": "Aline",
      "modelo": "modelo1",
      "id": 8
    }
  ]
}